PyDbSchema/Main.py
PyDbSchema/Schema.py
PyDbSchema/__init__.py
PyDbSchema-0.0.5.dist-info/Licence
PyDbSchema-0.0.5.dist-info/METADATA
PyDbSchema-0.0.5.dist-info/WHEEL
PyDbSchema-0.0.5.dist-info/top_level.txt
PyDbSchema-0.0.5.dist-info/RECORD
