Metadata-Version: 2.1
Name: PyDbSchema
Version: 0.0.5
Summary: PyMongoose enable you to validate your SChema and setting them default values it Give you Schema Object that give you easier accesbility of pymongo collection 
Home-page: https://github.com/yosiaLukumai/pymongo-wrappers
Author: Yosia Lukumai
Author-email: yosialukumai@gmail.com
License: MIT
Keywords: pythonmongodb,py_mongoose,Py_Mongoose,mongoosepy,pymongo,Schemavalidator,ShemaChecker
Platform: UNKNOWN
Classifier: Development Status :: 1 - Planning
Classifier: Intended Audience :: Developers
Classifier: Programming Language :: Python :: 3
Classifier: Operating System :: Unix
Classifier: Operating System :: MacOS :: MacOS X
Classifier: Operating System :: Microsoft :: Windows
License-File: Licence
Requires-Dist: pymongo (>=3.0)
